valorant_pro_api/__init__.py
valorant_pro_api/data.py
valorant_pro_api-1.1.1.dist-info/METADATA
valorant_pro_api-1.1.1.dist-info/WHEEL
valorant_pro_api-1.1.1.dist-info/licenses/LICENSE
valorant_pro_api-1.1.1.dist-info/RECORD
