Metadata-Version: 2.3
Name: Valorant-Pro-API
Version: 1.1.1
Summary: A python library to retrieve data from pro matches of valorant registered on the site https://vlr.gg/
Project-URL: Homepage, https://github.com/ThorkildFregi/Valorant-Pro-API
Project-URL: Issues, https://github.com/ThorkildFregi/Valorant-Pro-API/issues
Author-email: Gabriel Bermes--Poupeau <gabrielbermesp@gmail.com>
License-File: LICENSE
Classifier: License :: OSI Approved :: Apache Software License
Classifier: Operating System :: OS Independent
Classifier: Programming Language :: Python :: 3
Requires-Python: >=3.9
